{
  "components": {
    "schemas": {
      "Error": {
        "properties": {
          "code": {
            "description": "Error code",
            "type": "string"
          },
          "error": {
            "description": "Error message",
            "type": "string"
          }
        },
        "type": "object"
      },
      "Request": {
        "properties": {
          "expression": {
            "description": "Mathematical expression to evaluate",
            "type": "string"
          },
          "variables": {
            "description": "Variable values for evaluation",
            "type": "object"
          }
        },
        "required": [
          "expression"
        ],
        "type": "object"
      },
      "Response": {
        "properties": {
          "latex": {
            "description": "LaTeX representation",
            "type": "string"
          },
          "result": {
            "description": "Computed result",
            "type": "string"
          },
          "steps": {
            "description": "Step-by-step solution",
            "items": {
              "properties": {
                "description": {
                  "type": "string"
                },
                "expression": {
                  "type": "string"
                }
              },
              "type": "object"
            },
            "type": "array"
          }
        },
        "type": "object"
      }
    }
  },
  "info": {
    "description": "Complete guide to MathHook's Risch algorithm implementation for symbolic integration.\nCovers algorithm phases, implementation details, examples, non-elementary detection,\nlimitations, and future enhancements.\n",
    "title": "The Risch Algorithm in MathHook",
    "version": "1.0.0"
  },
  "openapi": "3.0.0",
  "paths": {
    "/appendix/risch_algorithm": {
      "post": {
        "description": "Complete guide to MathHook's Risch algorithm implementation for symbolic integration.\nCovers algorithm phases, implementation details, examples, non-elementary detection,\nlimitations, and future enhancements.\n",
        "requestBody": {
          "content": {
            "application/json": {
              "examples": {},
              "schema": {
                "$ref": "#/components/schemas/Request"
              }
            }
          },
          "required": true
        },
        "responses": {
          "200": {
            "content": {
              "application/json": {
                "examples": {},
                "schema": {
                  "$ref": "#/components/schemas/Response"
                }
              }
            },
            "description": "Successful computation"
          },
          "400": {
            "content": {
              "application/json": {
                "schema": {
                  "$ref": "#/components/schemas/Error"
                }
              }
            },
            "description": "Invalid input"
          }
        },
        "summary": "The Risch Algorithm in MathHook",
        "tags": [
          "appendix"
        ]
      }
    }
  },
  "servers": [
    {
      "description": "Production server",
      "url": "https://api.mathhook.org/v1"
    }
  ],
  "tags": [
    {
      "description": "appendix operations",
      "name": "appendix"
    }
  ]
}